README
setup.py
django_saddle.egg-info/PKG-INFO
django_saddle.egg-info/SOURCES.txt
django_saddle.egg-info/dependency_links.txt
django_saddle.egg-info/top_level.txt
saddle/__init__.py
saddle/settings_wrapper.py
saddle/urls.py
saddle/handlers/__init__.py
saddle/handlers/modpython.py
saddle/handlers/wsgi.py
saddle/management/__init__.py
saddle/management/commands/__init__.py